{"TV_Data": {"Channel_List": {"is_channel_list": true, "is_override": true, "thumb_width": 150, "all_Channels_Tab_Name": "", "main": {"id": 10, "name": "USA Channels", "sub_name": "Channels", "thumbnail_url": "https://www.iptv-updated.com/wp-content/uploads/2019/12/iconfinder_flag-usa_748050.png", "sub": {"sub_1": {"id": 1, "mode": "video", "name": "Newsy", "sub_name": "", "stream_video_url": "https://content.uplynk.com/channel/4bb4901b934c4e029fd4c1abfc766c37.m3u8?ad=newsyweb", "thumbnail_url": "https://www.iptv-updated.com/wp-content/themes/shootingstar-child/uploaded_images/newsy_img_2711.png"}, "sub_2": {"id": 2, "mode": "video", "name": "Newsy", "sub_name": "", "stream_video_url": "https://content.uplynk.com/channel/4bb4901b934c4e029fd4c1abfc766c37.m3u8", "thumbnail_url": "https://www.iptv-updated.com/wp-content/themes/shootingstar-child/uploaded_images/newsy_img_2711.png"}, "sub_3": {"id": 3, "mode": "website", "name_original": "", "name": "Play", "sub_name": "Win 10000", "website_url": "https://490.go.qureka.com/intro", "is_system_browser": true, "thumbnail_url": "https://raw.githubusercontent.com/kp-bitcoding/ad-manager/main/Interstitial/1.jpg", "thumbnail_url_original": ""}, "sub_4": {"id": 4, "mode": "video", "name": "Newsmax TV", "sub_name": "", "stream_video_url": "https://nmxlive.akamaized.net/hls/live/529965/Live_1/index_288.m3u8", "thumbnail_url": "https://www.iptv-updated.com/wp-content/themes/shootingstar-child/uploaded_images/newsmax_tv_img_2709.png"}, "sub_5": {"id": 5, "mode": "video", "name": "Newsmax TV", "sub_name": "", "stream_video_url": "https://nmxlive.akamaized.net/hls/live/529965/Live_1/index_720.m3u8", "thumbnail_url": "https://www.iptv-updated.com/wp-content/themes/shootingstar-child/uploaded_images/newsmax_tv_img_2709.png"}, "sub_6": {"id": 6, "mode": "website", "name_original": "", "name": "Play", "sub_name": "Win 20000", "website_url": "https://490.go.qureka.com/intro", "is_system_browser": true, "thumbnail_url": "https://raw.githubusercontent.com/kp-bitcoding/ad-manager/main/Interstitial/2.jpg", "thumbnail_url_original": ""}, "sub_7": {"id": 7, "mode": "video", "name": "NRBTV", "sub_name": "", "stream_video_url": "https://uni6rtmp.tulix.tv/nrbnetwork/myStream.sdp/playlist.m3u8", "thumbnail_url": "https://i.ytimg.com/vi/I58WfFz271Y/mqdefault.jpg"}, "sub_8": {"id": 8, "mode": "video", "name": "CBSN Minnesota", "sub_name": "", "stream_video_url": "https://dai.google.com/linear/hls/event/zcWPVCfURNSPxeidcckQLA/master.m3u8?iu=/4128/CBS.MINN.OTT", "thumbnail_url": "https://www.iptv-updated.com/wp-content/themes/shootingstar-child/uploaded_images/cbsn_minnesota_img_3237.png"}, "sub_9": {"id": 9, "mode": "website", "name_original": "", "name": "Play", "sub_name": "Win 30000", "website_url": "https://490.go.qureka.com/intro", "is_system_browser": true, "thumbnail_url": "https://raw.githubusercontent.com/kp-bitcoding/ad-manager/main/Interstitial/3.jpg", "thumbnail_url_original": ""}, "sub_10": {"id": 10, "mode": "video", "name": "The Asylum", "sub_name": "", "stream_video_url": "https://dai2.xumo.com/xumocdn/p=roku/amagi_hls_data_xumo1212A-theasylum/CDN/1280x720_2500000/index.m3u8", "thumbnail_url": "https://www.iptv-updated.com/wp-content/themes/shootingstar-child/uploaded_images/the_asylum_img_2778.png"}, "sub_11": {"id": 11, "mode": "video", "name": "3ABN KIDS TV", "sub_name": "", "stream_video_url": "https://moiptvhls-i.akamaihd.net/hls/live/652318/secure/master.m3u8", "thumbnail_url": ""}, "sub_12": {"id": 12, "mode": "website", "name_original": "", "name": "Play", "sub_name": "Win 40000", "website_url": "https://490.go.qureka.com/intro", "is_system_browser": true, "thumbnail_url": "https://raw.githubusercontent.com/kp-bitcoding/ad-manager/main/Interstitial/4.jpg", "thumbnail_url_original": ""}, "sub_13": {"id": 13, "mode": "video", "name": "Movie Kingdom", "sub_name": "", "stream_video_url": "https://a.jsrdn.com/broadcast/e9b4093a41/+0000/high/c.m3u8", "thumbnail_url": "https://www.iptv-updated.com/wp-content/themes/shootingstar-child/uploaded_images/movie_kingdom_img_2676.png"}, "sub_14": {"id": 14, "mode": "video", "name": "DC Council Channel", "sub_name": "", "stream_video_url": "http://video.oct.dc.gov/out/u/15_12.m3u8", "thumbnail_url": "https://www.iptv-updated.com/wp-content/themes/shootingstar-child/uploaded_images/default_img.png"}, "sub_15": {"id": 15, "mode": "website", "name_original": "", "name": "Play", "sub_name": "Win 50000", "website_url": "https://490.go.qureka.com/intro", "is_system_browser": true, "thumbnail_url": "https://raw.githubusercontent.com/kp-bitcoding/ad-manager/main/Interstitial/5.jpg", "thumbnail_url_original": ""}, "sub_16": {"id": 16, "mode": "video", "name": "Bek Sports East", "sub_name": "", "stream_video_url": "https://wowzaprod188-i.akamaihd.net/hls/live/728897/54d0bcd5/playlist.m3u8", "thumbnail_url": "https://www.iptv-updated.com/wp-content/themes/shootingstar-child/uploaded_images/bek_sports_east_img_2511.png"}, "sub_17": {"id": 17, "mode": "video", "name": "Bek Sports West", "sub_name": "", "stream_video_url": "https://wowzaprod188-i.akamaihd.net/hls/live/728897/89b077e6/playlist.m3u8", "thumbnail_url": "https://www.iptv-updated.com/wp-content/themes/shootingstar-child/uploaded_images/bek_sports_west_img_2512.png"}, "sub_18": {"id": 18, "mode": "website", "name_original": "", "name": "Play", "sub_name": "Win 60000", "website_url": "https://490.go.qureka.com/intro", "is_system_browser": true, "thumbnail_url": "https://raw.githubusercontent.com/kp-bitcoding/ad-manager/main/Interstitial/6.jpg", "thumbnail_url_original": ""}, "sub_19": {"id": 19, "mode": "video", "name": "BlazeTV", "sub_name": "", "stream_video_url": "https://theblaze4.akamaized.net/hls/live//699982/theblaze/cm-dvr/master.m3u8", "thumbnail_url": "https://www.iptv-updated.com/wp-content/themes/shootingstar-child/uploaded_images/blazetv_img_2521.png"}, "sub_20": {"id": 20, "mode": "video", "name": "AMG TV", "sub_name": "", "stream_video_url": "https://2-fss-2.streamhoster.com/pl_138/201660-1270634-1/playlist.m3u8", "thumbnail_url": "https://www.iptv-updated.com/wp-content/themes/shootingstar-child/uploaded_images/default_img.png"}, "sub_21": {"id": 21, "mode": "website", "name_original": "", "name": "Play", "sub_name": "Win 70000", "website_url": "https://490.go.qureka.com/intro", "is_system_browser": true, "thumbnail_url": "https://raw.githubusercontent.com/kp-bitcoding/ad-manager/main/Interstitial/7.jpg", "thumbnail_url_original": ""}, "sub_22": {"id": 22, "mode": "video", "name": "Duck TV", "sub_name": "", "stream_video_url": "https://mmm-ducktv-2-it.samsung.wurl.com/manifest/playlist.m3u8", "thumbnail_url": "https://www.iptv-updated.com/wp-content/themes/shootingstar-child/uploaded_images/duck_tv_img_2588.png"}, "sub_23": {"id": 23, "mode": "video", "name": "Black Cinema", "sub_name": "", "stream_video_url": "https://stitcher.pluto.tv/stitch/hls/channel/561c5b0dada51f8004c4d855/master.m3u8?deviceType=web&deviceMake=Chrome&deviceModel=Chrome&sid=6e360db0-724b-11e8-be77-bf4d1417b012&deviceId=889540f0-712d-11e8-b9ec-8ba319deeadf&deviceVersion=37.0.2049.0&appVersion=2.0.0&deviceDNT=0&userId=&advertisingId=&deviceLat=38.5783&deviceLon=-90.6666&app_name=&appName=&appStoreUrl=&serverSideAds=true", "thumbnail_url": "https://www.iptv-updated.com/wp-content/themes/shootingstar-child/uploaded_images/black_cinema_img_2519.png"}, "sub_24": {"id": 24, "mode": "website", "name_original": "", "name": "Play", "sub_name": "Win 10000", "website_url": "https://490.go.qureka.com/intro", "is_system_browser": true, "thumbnail_url": "https://raw.githubusercontent.com/kp-bitcoding/ad-manager/main/Interstitial/1.jpg", "thumbnail_url_original": ""}, "sub_25": {"id": 25, "mode": "video", "name": "LoveWorld USA", "sub_name": "", "stream_video_url": "https://loveworldusa-lh.akamaihd.net/i/lwusa2_1@514985/master.m3u8", "thumbnail_url": "https://www.iptv-updated.com/wp-content/themes/shootingstar-child/uploaded_images/loveworld_usa_img_2667.png"}, "sub_26": {"id": 26, "mode": "video", "name": "Leominster TV Public", "sub_name": "", "stream_video_url": "http://gov.leominster.tv/Pub/smil:Pub.smil/chunklist_w2036537178_b1344100_sleng_t64NzIwcA==.m3u8", "thumbnail_url": "https://www.iptv-updated.com/wp-content/themes/shootingstar-child/uploaded_images/leominster_tv_public_img_2663.png"}, "sub_27": {"id": 27, "mode": "website", "name_original": "", "name": "Play", "sub_name": "Win 20000", "website_url": "https://490.go.qureka.com/intro", "is_system_browser": true, "thumbnail_url": "https://raw.githubusercontent.com/kp-bitcoding/ad-manager/main/Interstitial/2.jpg", "thumbnail_url_original": ""}, "sub_28": {"id": 28, "mode": "video", "name": "Leominster TV Public", "sub_name": "", "stream_video_url": "http://gov.leominster.tv/Pub/smil:Pub.smil/playlist.m3u8", "thumbnail_url": "https://www.iptv-updated.com/wp-content/themes/shootingstar-child/uploaded_images/leominster_tv_public_img_2663.png"}, "sub_29": {"id": 29, "mode": "video", "name": "Leominster TV Educational", "sub_name": "", "stream_video_url": "http://edu.leominster.tv/Edu/smil:Edu.smil/chunklist_w43731873_b1344100_sleng_t64NzIwcA==.m3u8", "thumbnail_url": "https://www.iptv-updated.com/wp-content/themes/shootingstar-child/uploaded_images/leominster_tv_educational_img_2661.png"}, "sub_30": {"id": 30, "mode": "website", "name_original": "", "name": "Play", "sub_name": "Win 30000", "website_url": "https://490.go.qureka.com/intro", "is_system_browser": true, "thumbnail_url": "https://raw.githubusercontent.com/kp-bitcoding/ad-manager/main/Interstitial/3.jpg", "thumbnail_url_original": ""}, "sub_31": {"id": 31, "mode": "video", "name": "Leominster TV Educational", "sub_name": "", "stream_video_url": "http://edu.leominster.tv/Edu/smil:Edu.smil/playlist.m3u8", "thumbnail_url": "https://www.iptv-updated.com/wp-content/themes/shootingstar-child/uploaded_images/leominster_tv_educational_img_2661.png"}, "sub_32": {"id": 32, "mode": "video", "name": "ET Live", "sub_name": "", "stream_video_url": "https://etlive-mediapackage-fastly.cbsaavideo.com/dvr/manifest.m3u8?iu=/8264/vaw-can/desktop/cbslocal", "thumbnail_url": "https://www.iptv-updated.com/wp-content/themes/shootingstar-child/uploaded_images/et_live_img_2594.png"}, "sub_33": {"id": 33, "mode": "website", "name_original": "", "name": "Play", "sub_name": "Win 40000", "website_url": "https://490.go.qureka.com/intro", "is_system_browser": true, "thumbnail_url": "https://raw.githubusercontent.com/kp-bitcoding/ad-manager/main/Interstitial/4.jpg", "thumbnail_url_original": ""}, "sub_34": {"id": 34, "mode": "video", "name": "Law And Crime Network", "sub_name": "", "stream_video_url": "https://dai2.xumo.com/amagi_hls_data_xumo1234A-lawcrime/CDN/master.m3u8", "thumbnail_url": "https://www.iptv-updated.com/wp-content/themes/shootingstar-child/uploaded_images/law_and_crime_network_img_2660.png"}, "sub_35": {"id": 35, "mode": "video", "name": "Stadium", "sub_name": "", "stream_video_url": "https://d28avce4cnwu2y.cloudfront.net/v1/manifest/61a556f78e4547c8ab5c6297ea291d6350767ca2/Mux/37f5dd6d-5713-4998-8354-8c6675612b42/0.m3u8", "thumbnail_url": "https://www.iptv-updated.com/wp-content/themes/shootingstar-child/uploaded_images/stadium_img_2768.png"}, "sub_36": {"id": 36, "mode": "website", "name_original": "", "name": "Play", "sub_name": "Win 50000", "website_url": "https://490.go.qureka.com/intro", "is_system_browser": true, "thumbnail_url": "https://raw.githubusercontent.com/kp-bitcoding/ad-manager/main/Interstitial/5.jpg", "thumbnail_url_original": ""}, "sub_37": {"id": 37, "mode": "video", "name": "Stadium", "sub_name": "", "stream_video_url": "https://stadiumlivein-i.akamaihd.net/hls/live/522512/mux_4/master.m3u8", "thumbnail_url": "https://www.iptv-updated.com/wp-content/themes/shootingstar-child/uploaded_images/stadium_img_2768.png"}, "sub_38": {"id": 38, "mode": "video", "name": "Stadium", "sub_name": "", "stream_video_url": "https://d28avce4cnwu2y.cloudfront.net/v1/manifest/61a556f78e4547c8ab5c6297ea291d6350767ca2/Mux/37f5dd6d-5713-4998-8354-8c6675612b42/4.m3u8", "thumbnail_url": "https://www.iptv-updated.com/wp-content/themes/shootingstar-child/uploaded_images/stadium_img_2768.png"}, "sub_39": {"id": 39, "mode": "website", "name_original": "", "name": "Play", "sub_name": "Win 60000", "website_url": "https://490.go.qureka.com/intro", "is_system_browser": true, "thumbnail_url": "https://raw.githubusercontent.com/kp-bitcoding/ad-manager/main/Interstitial/6.jpg", "thumbnail_url_original": ""}, "sub_40": {"id": 40, "mode": "video", "name": "AKC TV", "sub_name": "", "stream_video_url": "https://video.blivenyc.com/broadcast/prod/2061/22/desktop-playlist.m3u8", "thumbnail_url": "https://www.iptv-updated.com/wp-content/themes/shootingstar-child/uploaded_images/akc_tv_img_2493.png"}, "sub_41": {"id": 41, "mode": "video", "name": "AKC TV", "sub_name": "", "stream_video_url": "https://video.blivenyc.com/broadcast/prod/2061/22/file-3192k.m3u8", "thumbnail_url": "https://www.iptv-updated.com/wp-content/themes/shootingstar-child/uploaded_images/akc_tv_img_2493.png"}, "sub_42": {"id": 42, "mode": "website", "name_original": "", "name": "Play", "sub_name": "Win 70000", "website_url": "https://490.go.qureka.com/intro", "is_system_browser": true, "thumbnail_url": "https://raw.githubusercontent.com/kp-bitcoding/ad-manager/main/Interstitial/7.jpg", "thumbnail_url_original": ""}, "sub_43": {"id": 43, "mode": "video", "name": "GOD TV", "sub_name": "", "stream_video_url": "https://zypelive-lh.akamaihd.net/i/default_1@710958/master.m3u8", "thumbnail_url": "https://www.iptv-updated.com/wp-content/themes/shootingstar-child/uploaded_images/god_tv_img_2623.png"}, "sub_44": {"id": 44, "mode": "video", "name": "GOD TV", "sub_name": "", "stream_video_url": "https://zypelive-lh.akamaihd.net/i/default_1@745545/master.m3u8", "thumbnail_url": "https://www.iptv-updated.com/wp-content/themes/shootingstar-child/uploaded_images/god_tv_img_2623.png"}, "sub_45": {"id": 45, "mode": "website", "name_original": "", "name": "Play", "sub_name": "Win 10000", "website_url": "https://490.go.qureka.com/intro", "is_system_browser": true, "thumbnail_url": "https://raw.githubusercontent.com/kp-bitcoding/ad-manager/main/Interstitial/1.jpg", "thumbnail_url_original": ""}, "sub_46": {"id": 46, "mode": "video", "name": "ABC 2 Baton Rouge LA (WBRZ-HD)", "sub_name": "", "stream_video_url": "http://cms-wowza.lunabyte.io/wbrz-live-1/_definst_/smil:wbrz-live.smil/chunklist_b1300000.m3u8?fluxustv.m3u8", "thumbnail_url": "https://www.iptv-updated.com/wp-content/themes/shootingstar-child/uploaded_images/abc_2_baton_rouge_la_(wbrz-hd)_img_2478.png"}, "sub_47": {"id": 47, "mode": "video", "name": "ABC 2 Baton Rouge LA (WBRZ-HD)", "sub_name": "", "stream_video_url": "http://cms-wowza.lunabyte.io/wbrz-live-1/_definst_/smil:wbrz-live.smil/playlist.m3u8", "thumbnail_url": "https://www.iptv-updated.com/wp-content/themes/shootingstar-child/uploaded_images/abc_2_baton_rouge_la_(wbrz-hd)_img_2478.png"}, "sub_48": {"id": 48, "mode": "website", "name_original": "", "name": "Play", "sub_name": "Win 20000", "website_url": "https://490.go.qureka.com/intro", "is_system_browser": true, "thumbnail_url": "https://raw.githubusercontent.com/kp-bitcoding/ad-manager/main/Interstitial/2.jpg", "thumbnail_url_original": ""}, "sub_49": {"id": 49, "mode": "video", "name": "Better Nature TV", "sub_name": "", "stream_video_url": "http://uni5rtmp.tulix.tv:1935/betternature/betternature/playlist.m3u8", "thumbnail_url": "https://www.iptv-updated.com/wp-content/themes/shootingstar-child/uploaded_images/better_nature_tv_img_2517.png"}, "sub_50": {"id": 50, "mode": "video", "name": "Bible Explorations", "sub_name": "", "stream_video_url": "http://stream.iphonewebtown.com:1935/bibleexplorations/bexplorationsmobile.stream/playlist.m3u8", "thumbnail_url": "https://www.iptv-updated.com/wp-content/themes/shootingstar-child/uploaded_images/bible_explorations_img_2518.png"}, "sub_51": {"id": 51, "mode": "website", "name_original": "", "name": "Play", "sub_name": "Win 30000", "website_url": "https://490.go.qureka.com/intro", "is_system_browser": true, "thumbnail_url": "https://raw.githubusercontent.com/kp-bitcoding/ad-manager/main/Interstitial/3.jpg", "thumbnail_url_original": ""}, "sub_52": {"id": 52, "mode": "video", "name": "C-Span 2", "sub_name": "", "stream_video_url": "https://skystreams-lh.akamaihd.net/i/SkyC2_1@500807/master.m3u8", "thumbnail_url": "https://www.iptv-updated.com/wp-content/themes/shootingstar-child/uploaded_images/c-span_2_img_2537.png"}, "sub_53": {"id": 53, "mode": "video", "name": "C-Span 3", "sub_name": "", "stream_video_url": "https://skystreams-lh.akamaihd.net/i/SkyC3_1@500808/master.m3u8", "thumbnail_url": "https://www.iptv-updated.com/wp-content/themes/shootingstar-child/uploaded_images/c-span_3_img_2538.png"}, "sub_54": {"id": 54, "mode": "website", "name_original": "", "name": "Play", "sub_name": "Win 40000", "website_url": "https://490.go.qureka.com/intro", "is_system_browser": true, "thumbnail_url": "https://raw.githubusercontent.com/kp-bitcoding/ad-manager/main/Interstitial/4.jpg", "thumbnail_url_original": ""}, "sub_55": {"id": 55, "mode": "video", "name": "Cerritos TV3", "sub_name": "", "stream_video_url": "https://granicusliveus4-a.akamaihd.net/cerritos/G0010_002/chunklist.m3u8", "thumbnail_url": "https://www.iptv-updated.com/wp-content/themes/shootingstar-child/uploaded_images/default_img.png"}, "sub_56": {"id": 56, "mode": "video", "name": "Christian Youth Channel", "sub_name": "", "stream_video_url": "http://media.smc-host.com:1935/cycnow.com/cyc2/chunklist_w884806316.m3u8", "thumbnail_url": "https://www.iptv-updated.com/wp-content/themes/shootingstar-child/uploaded_images/christian_youth_channel_img_2559.png"}, "sub_57": {"id": 57, "mode": "website", "name_original": "", "name": "Play", "sub_name": "Win 50000", "website_url": "https://490.go.qureka.com/intro", "is_system_browser": true, "thumbnail_url": "https://raw.githubusercontent.com/kp-bitcoding/ad-manager/main/Interstitial/5.jpg", "thumbnail_url_original": ""}, "sub_58": {"id": 58, "mode": "video", "name": "CT-N Court Feed", "sub_name": "", "stream_video_url": "http://video.ct-n.com/live/ctnSupreme/chunklist_w538335829_DVR.m3u8", "thumbnail_url": "https://www.iptv-updated.com/wp-content/themes/shootingstar-child/uploaded_images/ct-n_court_feed_img_2570.png"}, "sub_59": {"id": 59, "mode": "video", "name": "CT-N Court Feed", "sub_name": "", "stream_video_url": "http://video.ct-n.com/live/ctnSupreme/chunklist_DVR.m3u8", "thumbnail_url": "https://www.iptv-updated.com/wp-content/themes/shootingstar-child/uploaded_images/ct-n_court_feed_img_2570.png"}, "sub_60": {"id": 60, "mode": "website", "name_original": "", "name": "Play", "sub_name": "Win 60000", "website_url": "https://490.go.qureka.com/intro", "is_system_browser": true, "thumbnail_url": "https://raw.githubusercontent.com/kp-bitcoding/ad-manager/main/Interstitial/6.jpg", "thumbnail_url_original": ""}, "sub_61": {"id": 61, "mode": "video", "name": "CT-N Live Stream 2", "sub_name": "", "stream_video_url": "http://video.ct-n.com/live/web2stream/chunklist_w1202315245_DVR.m3u8", "thumbnail_url": "https://www.iptv-updated.com/wp-content/themes/shootingstar-child/uploaded_images/ct-n_live_stream_2_img_2573.png"}, "sub_62": {"id": 62, "mode": "video", "name": "CT-N Live Stream 2", "sub_name": "", "stream_video_url": "http://video.ct-n.com/live/web2stream/playlist.m3u8", "thumbnail_url": "https://www.iptv-updated.com/wp-content/themes/shootingstar-child/uploaded_images/ct-n_live_stream_2_img_2573.png"}, "sub_63": {"id": 63, "mode": "website", "name_original": "", "name": "Play", "sub_name": "Win 70000", "website_url": "https://490.go.qureka.com/intro", "is_system_browser": true, "thumbnail_url": "https://raw.githubusercontent.com/kp-bitcoding/ad-manager/main/Interstitial/7.jpg", "thumbnail_url_original": ""}, "sub_64": {"id": 64, "mode": "video", "name": "CTN", "sub_name": "", "stream_video_url": "http://rrsatrtmp.tulix.tv/ctntv/ctntvmulti.smil/chunklist_w846886780_b1764000.m3u8?fluxustv.m3u8", "thumbnail_url": "https://www.iptv-updated.com/wp-content/themes/shootingstar-child/uploaded_images/ctn_img_2574.png"}, "sub_65": {"id": 65, "mode": "video", "name": "CTN", "sub_name": "", "stream_video_url": "http://rtmp.ottdemo.rrsat.com/ctntv/ctntvmulti.smil/chunklist.m3u8", "thumbnail_url": "https://www.iptv-updated.com/wp-content/themes/shootingstar-child/uploaded_images/ctn_img_2574.png"}, "sub_66": {"id": 66, "mode": "website", "name_original": "", "name": "Play", "sub_name": "Win 10000", "website_url": "https://490.go.qureka.com/intro", "is_system_browser": true, "thumbnail_url": "https://raw.githubusercontent.com/kp-bitcoding/ad-manager/main/Interstitial/1.jpg", "thumbnail_url_original": ""}, "sub_67": {"id": 67, "mode": "video", "name": "CTNi", "sub_name": "", "stream_video_url": "http://184.164.158.202:1936/48/smil:48.smil/playlist.m3u8", "thumbnail_url": "https://www.iptv-updated.com/wp-content/themes/shootingstar-child/uploaded_images/ctni_img_2575.png"}, "sub_68": {"id": 68, "mode": "video", "name": "CTNi", "sub_name": "", "stream_video_url": "http://184.164.158.202:1936/48/smil:48.smil/playlist.m3u8?iptvgratis?chile.m3u8", "thumbnail_url": "https://www.iptv-updated.com/wp-content/themes/shootingstar-child/uploaded_images/ctni_img_2575.png"}, "sub_69": {"id": 69, "mode": "website", "name_original": "", "name": "Play", "sub_name": "Win 20000", "website_url": "https://490.go.qureka.com/intro", "is_system_browser": true, "thumbnail_url": "https://raw.githubusercontent.com/kp-bitcoding/ad-manager/main/Interstitial/2.jpg", "thumbnail_url_original": ""}, "sub_70": {"id": 70, "mode": "video", "name": "Denver 8 TV", "sub_name": "", "stream_video_url": "https://granicusliveus8-a.akamaihd.net/denver/G0080_002/chunklist.m3u8", "thumbnail_url": "https://www.iptv-updated.com/wp-content/themes/shootingstar-child/uploaded_images/denver_8_tv_img_2580.png"}, "sub_71": {"id": 71, "mode": "video", "name": "District of Columbia Network", "sub_name": "", "stream_video_url": "http://video.oct.dc.gov/out/u/DCN.m3u8", "thumbnail_url": "https://www.iptv-updated.com/wp-content/themes/shootingstar-child/uploaded_images/district_of_columbia_network_img_2581.png"}, "sub_72": {"id": 72, "mode": "website", "name_original": "", "name": "Play", "sub_name": "Win 30000", "website_url": "https://490.go.qureka.com/intro", "is_system_browser": true, "thumbnail_url": "https://raw.githubusercontent.com/kp-bitcoding/ad-manager/main/Interstitial/3.jpg", "thumbnail_url_original": ""}, "sub_73": {"id": 73, "mode": "video", "name": "Divine Vision", "sub_name": "", "stream_video_url": "http://divineplayout-us2.tulix.tv/live/Stream1/.m3u8", "thumbnail_url": "https://www.iptv-updated.com/wp-content/themes/shootingstar-child/uploaded_images/divine_vision_img_2582.png"}, "sub_74": {"id": 74, "mode": "video", "name": "Divine Vision", "sub_name": "", "stream_video_url": "https://divineplayout-us2.tulix.tv/live/Stream1/.m3u8", "thumbnail_url": "https://www.iptv-updated.com/wp-content/themes/shootingstar-child/uploaded_images/divine_vision_img_2582.png"}, "sub_75": {"id": 75, "mode": "website", "name_original": "", "name": "Play", "sub_name": "Win 40000", "website_url": "https://490.go.qureka.com/intro", "is_system_browser": true, "thumbnail_url": "https://raw.githubusercontent.com/kp-bitcoding/ad-manager/main/Interstitial/4.jpg", "thumbnail_url_original": ""}, "sub_76": {"id": 76, "mode": "video", "name": "Dr. Gene Scott", "sub_name": "", "stream_video_url": "https://wescottcchls-lh.akamaihd.net/i/wcc_wowlivehls@24607/master.m3u8", "thumbnail_url": "https://www.iptv-updated.com/wp-content/themes/shootingstar-child/uploaded_images/dr._gene_scott_img_2586.png"}, "sub_77": {"id": 77, "mode": "video", "name": "Akaku 53 (Hawaii)", "sub_name": "", "stream_video_url": "https://akaku.vod.castus.tv/live/ch1.m3u8", "thumbnail_url": "https://www.iptv-updated.com/wp-content/themes/shootingstar-child/uploaded_images/akaku_53_(hawaii)_img_2490.png"}, "sub_78": {"id": 78, "mode": "website", "name_original": "", "name": "Play", "sub_name": "Win 50000", "website_url": "https://490.go.qureka.com/intro", "is_system_browser": true, "thumbnail_url": "https://raw.githubusercontent.com/kp-bitcoding/ad-manager/main/Interstitial/5.jpg", "thumbnail_url_original": ""}, "sub_79": {"id": 79, "mode": "video", "name": "FOX 28 Savannah GA (WTGS)", "sub_name": "", "stream_video_url": "https://content.uplynk.com/channel/e56ba52a1b9d45ad8c8a033fd83fe480.m3u8", "thumbnail_url": "https://www.iptv-updated.com/wp-content/themes/shootingstar-child/uploaded_images/fox_28_savannah_ga_(wtgs)_img_2604.png"}, "sub_80": {"id": 80, "mode": "video", "name": "Akaku 54 (Hawaii)", "sub_name": "", "stream_video_url": "https://akaku.vod.castus.tv/live/ch2.m3u8", "thumbnail_url": "https://www.iptv-updated.com/wp-content/themes/shootingstar-child/uploaded_images/akaku_54_(hawaii)_img_2491.png"}, "sub_81": {"id": 81, "mode": "website", "name_original": "", "name": "Play", "sub_name": "Win 60000", "website_url": "https://490.go.qureka.com/intro", "is_system_browser": true, "thumbnail_url": "https://raw.githubusercontent.com/kp-bitcoding/ad-manager/main/Interstitial/6.jpg", "thumbnail_url_original": ""}, "sub_82": {"id": 82, "mode": "video", "name": "HSN", "sub_name": "", "stream_video_url": "https://v-pi.mybtv.net/event/41.1/640x480?start_time=2019-12-20T23%3A45%3A00.000Z&end_time=2028&env=prd&uid=29375", "thumbnail_url": "https://www.iptv-updated.com/wp-content/themes/shootingstar-child/uploaded_images/hsn_img_2632.png"}, "sub_83": {"id": 83, "mode": "video", "name": "HSN", "sub_name": "", "stream_video_url": "https://hsn2html5-lh.akamaihd.net/i/hsn2html5_01@13178/master.m3u8", "thumbnail_url": "https://www.iptv-updated.com/wp-content/themes/shootingstar-child/uploaded_images/hsn_img_2632.png"}, "sub_84": {"id": 84, "mode": "website", "name_original": "", "name": "Play", "sub_name": "Win 70000", "website_url": "https://490.go.qureka.com/intro", "is_system_browser": true, "thumbnail_url": "https://raw.githubusercontent.com/kp-bitcoding/ad-manager/main/Interstitial/7.jpg", "thumbnail_url_original": ""}, "sub_85": {"id": 85, "mode": "video", "name": "Hunt Channel", "sub_name": "", "stream_video_url": "https://1111296894.rsc.cdn77.org/LS-ATL-56868-1/index.m3u8", "thumbnail_url": "https://www.iptv-updated.com/wp-content/themes/shootingstar-child/uploaded_images/hunt_channel_img_2633.png"}, "sub_86": {"id": 86, "mode": "video", "name": "Hunt Channel", "sub_name": "", "stream_video_url": "https://1111296894.rsc.cdn77.org/LS-ATL-56868-1/tracks-v1a1/mono.m3u8", "thumbnail_url": "https://www.iptv-updated.com/wp-content/themes/shootingstar-child/uploaded_images/hunt_channel_img_2633.png"}, "sub_87": {"id": 87, "mode": "website", "name_original": "", "name": "Play", "sub_name": "Win 10000", "website_url": "https://490.go.qureka.com/intro", "is_system_browser": true, "thumbnail_url": "https://raw.githubusercontent.com/kp-bitcoding/ad-manager/main/Interstitial/1.jpg", "thumbnail_url_original": ""}, "sub_88": {"id": 88, "mode": "video", "name": "Inspiration TV", "sub_name": "", "stream_video_url": "https://inspnetworks-lh.akamaihd.net/i/insp_2@393793/master.m3u8", "thumbnail_url": "https://www.iptv-updated.com/wp-content/themes/shootingstar-child/uploaded_images/inspiration_tv_img_2635.png"}, "sub_89": {"id": 89, "mode": "video", "name": "ISN", "sub_name": "", "stream_video_url": "http://cpdc101-lh.akamaihd.net/i/ISNCPDCMB1_1@314337/master.m3u8", "thumbnail_url": "https://www.iptv-updated.com/wp-content/themes/shootingstar-child/uploaded_images/isn_img_2637.png"}, "sub_90": {"id": 90, "mode": "website", "name_original": "", "name": "Play", "sub_name": "Win 20000", "website_url": "https://490.go.qureka.com/intro", "is_system_browser": true, "thumbnail_url": "https://raw.githubusercontent.com/kp-bitcoding/ad-manager/main/Interstitial/2.jpg", "thumbnail_url_original": ""}, "sub_91": {"id": 91, "mode": "video", "name": "JBS", "sub_name": "", "stream_video_url": "http://uni8rtmp.tulix.tv:1935/shalomtv-pc/smil:shalomtv.smil/master.m3u8", "thumbnail_url": "https://www.iptv-updated.com/wp-content/themes/shootingstar-child/uploaded_images/jbs_img_2639.png"}, "sub_92": {"id": 92, "mode": "video", "name": "Key TV", "sub_name": "", "stream_video_url": "http://media4.tripsmarter.com:1935/LiveTV/KTVHD/chunklist_w363623166.m3u8", "thumbnail_url": "https://www.iptv-updated.com/wp-content/themes/shootingstar-child/uploaded_images/key_tv_img_2646.png"}, "sub_93": {"id": 93, "mode": "website", "name_original": "", "name": "Play", "sub_name": "Win 30000", "website_url": "https://490.go.qureka.com/intro", "is_system_browser": true, "thumbnail_url": "https://raw.githubusercontent.com/kp-bitcoding/ad-manager/main/Interstitial/3.jpg", "thumbnail_url_original": ""}, "sub_94": {"id": 94, "mode": "video", "name": "KOMO News (KOMO-TV)", "sub_name": "", "stream_video_url": "https://content.uplynk.com/2c88dfe19e1447e6a6aa27e8e143a140.m3u8", "thumbnail_url": "https://www.iptv-updated.com/wp-content/themes/shootingstar-child/uploaded_images/komo_news_(komo-tv)_img_2651.png"}, "sub_95": {"id": 95, "mode": "video", "name": "KTLA 5", "sub_name": "", "stream_video_url": "https://content.uplynk.com/channel/6cbf2d32a5384dc1b787539b1102433c.m3u8", "thumbnail_url": "https://www.iptv-updated.com/wp-content/themes/shootingstar-child/uploaded_images/ktla_5_img_2201.png"}, "sub_96": {"id": 96, "mode": "website", "name_original": "", "name": "Play", "sub_name": "Win 40000", "website_url": "https://490.go.qureka.com/intro", "is_system_browser": true, "thumbnail_url": "https://raw.githubusercontent.com/kp-bitcoding/ad-manager/main/Interstitial/4.jpg", "thumbnail_url_original": ""}, "sub_97": {"id": 97, "mode": "video", "name": "Leominster TV Government", "sub_name": "", "stream_video_url": "http://gov.leominster.tv/Gov/smil:Gov.smil/chunklist_w1957429215_b1344100_sleng_t64NzIwcA==.m3u8", "thumbnail_url": "https://www.iptv-updated.com/wp-content/themes/shootingstar-child/uploaded_images/leominster_tv_government_img_2662.png"}, "sub_98": {"id": 98, "mode": "video", "name": "Leominster TV Government", "sub_name": "", "stream_video_url": "http://gov.leominster.tv/Gov/smil:Gov.smil/chunklist_w1957429215_b1344100_sleng_t64NzIwcA==.m3u8?fluxustv.m3u8", "thumbnail_url": "https://www.iptv-updated.com/wp-content/themes/shootingstar-child/uploaded_images/leominster_tv_government_img_2662.png"}, "sub_99": {"id": 99, "mode": "website", "name_original": "", "name": "Play", "sub_name": "Win 50000", "website_url": "https://490.go.qureka.com/intro", "is_system_browser": true, "thumbnail_url": "https://raw.githubusercontent.com/kp-bitcoding/ad-manager/main/Interstitial/5.jpg", "thumbnail_url_original": ""}, "sub_100": {"id": 100, "mode": "video", "name": "Lex TV", "sub_name": "", "stream_video_url": "http://granicusliveus2-a.akamaihd.net/lfucg/G0264_002/chunklist_w831870727.m3u8", "thumbnail_url": "https://www.iptv-updated.com/wp-content/themes/shootingstar-child/uploaded_images/lex_tv_img_2664.png"}, "sub_101": {"id": 101, "mode": "video", "name": "Lex TV", "sub_name": "", "stream_video_url": "http://granicusliveus2-a.akamaihd.net/lfucg/G0264_002/chunklist_w831870727.m3u8?fluxustv.m3u8", "thumbnail_url": "https://www.iptv-updated.com/wp-content/themes/shootingstar-child/uploaded_images/lex_tv_img_2664.png"}, "sub_102": {"id": 102, "mode": "website", "name_original": "", "name": "Play", "sub_name": "Win 60000", "website_url": "https://490.go.qureka.com/intro", "is_system_browser": true, "thumbnail_url": "https://raw.githubusercontent.com/kp-bitcoding/ad-manager/main/Interstitial/6.jpg", "thumbnail_url_original": ""}, "sub_103": {"id": 103, "mode": "video", "name": "LifevisionTV", "sub_name": "", "stream_video_url": "http://uni5rtmp.tulix.tv/lifevision/lifevision.stream/playlist.m3u8", "thumbnail_url": "https://www.iptv-updated.com/wp-content/themes/shootingstar-child/uploaded_images/lifevisiontv_img_2665.png"}, "sub_104": {"id": 104, "mode": "video", "name": "LifevisionTV", "sub_name": "", "stream_video_url": "https://uni5rtmp.tulix.tv/lifevision/lifevision.stream/playlist.m3u8", "thumbnail_url": "https://www.iptv-updated.com/wp-content/themes/shootingstar-child/uploaded_images/lifevisiontv_img_2665.png"}, "sub_105": {"id": 105, "mode": "website", "name_original": "", "name": "Play", "sub_name": "Win 70000", "website_url": "https://490.go.qureka.com/intro", "is_system_browser": true, "thumbnail_url": "https://raw.githubusercontent.com/kp-bitcoding/ad-manager/main/Interstitial/7.jpg", "thumbnail_url_original": ""}, "sub_106": {"id": 106, "mode": "video", "name": "3News Now (KMTV-TV)", "sub_name": "", "stream_video_url": "https://content.uplynk.com/channel/328d1434fb51476cb6567c74d5b2cc70.m3u8", "thumbnail_url": "https://www.iptv-updated.com/wp-content/themes/shootingstar-child/uploaded_images/3news_now_(kmtv-tv)_img_2475.png"}, "sub_107": {"id": 107, "mode": "video", "name": "NBC 15 Madison WI (WMTVNBC)", "sub_name": "", "stream_video_url": "http://ad-playlistserver.aws.syncbak.com/playlist/899088/master.m3u8?access_token=eyJhbGciOiJIUzI1NiIsImtpZCI6IkdyYXkyMDE2MDgyOSIsInN1YiI6IioiLCJ0eXAiOiJKV1QifQ.eyJleHAiOjE3OTAzNjkxMDUsImlzcyI6IldMUyIsIm1kNSI6ImJhZTU4Y2ZlZWM2NmU1MjZkNmVjZmE1YmUzNTQxMzQ4IiwibWlkIjoiODk5MDg4In0.vBWkHmqS3z3dpq8UWfbk4wFd-vQlj6B0up-rpt7X_7Q", "thumbnail_url": "https://www.iptv-updated.com/wp-content/themes/shootingstar-child/uploaded_images/nbc_15_madison_wi_(wmtvnbc)_img_2690.png"}, "sub_108": {"id": 108, "mode": "website", "name_original": "", "name": "Play", "sub_name": "Win 10000", "website_url": "https://490.go.qureka.com/intro", "is_system_browser": true, "thumbnail_url": "https://raw.githubusercontent.com/kp-bitcoding/ad-manager/main/Interstitial/1.jpg", "thumbnail_url_original": ""}, "sub_109": {"id": 109, "mode": "video", "name": "NBC 26 (WGBA)", "sub_name": "", "stream_video_url": "https://content.uplynk.com/channel/1fbfb28ae5044f619f75ae0adb011989.m3u8", "thumbnail_url": "https://www.iptv-updated.com/wp-content/themes/shootingstar-child/uploaded_images/nbc_26_(wgba)_img_2691.png"}, "sub_110": {"id": 110, "mode": "video", "name": "23 ABC (KERO)", "sub_name": "", "stream_video_url": "https://content.uplynk.com/channel/ff809e6d9ec34109abfb333f0d4444b5.m3u8", "thumbnail_url": "https://www.iptv-updated.com/wp-content/themes/shootingstar-child/uploaded_images/default_img.png"}, "sub_111": {"id": 111, "mode": "website", "name_original": "", "name": "Play", "sub_name": "Win 20000", "website_url": "https://490.go.qureka.com/intro", "is_system_browser": true, "thumbnail_url": "https://raw.githubusercontent.com/kp-bitcoding/ad-manager/main/Interstitial/2.jpg", "thumbnail_url_original": ""}, "sub_112": {"id": 112, "mode": "video", "name": "Olelo 53", "sub_name": "", "stream_video_url": "http://granicusliveus12-a.akamaihd.net/olelo/G0125_011/chunklist.m3u8", "thumbnail_url": "https://www.iptv-updated.com/wp-content/themes/shootingstar-child/uploaded_images/default_img.png"}, "sub_113": {"id": 113, "mode": "video", "name": "Olelo 54", "sub_name": "", "stream_video_url": "http://granicusliveus12-a.akamaihd.net/olelo/G0125_012/chunklist.m3u8", "thumbnail_url": "https://www.iptv-updated.com/wp-content/themes/shootingstar-child/uploaded_images/default_img.png"}, "sub_114": {"id": 114, "mode": "website", "name_original": "", "name": "Play", "sub_name": "Win 30000", "website_url": "https://490.go.qureka.com/intro", "is_system_browser": true, "thumbnail_url": "https://raw.githubusercontent.com/kp-bitcoding/ad-manager/main/Interstitial/3.jpg", "thumbnail_url_original": ""}, "sub_115": {"id": 115, "mode": "video", "name": "Olelo 55", "sub_name": "", "stream_video_url": "http://granicusliveus12-a.akamaihd.net/olelo/G0125_013/chunklist.m3u8", "thumbnail_url": "https://www.iptv-updated.com/wp-content/themes/shootingstar-child/uploaded_images/default_img.png"}, "sub_116": {"id": 116, "mode": "video", "name": "Olelo 55", "sub_name": "", "stream_video_url": "https://granicusliveus12-a.akamaihd.net/olelo/G0125_013/chunklist.m3u8", "thumbnail_url": "https://www.iptv-updated.com/wp-content/themes/shootingstar-child/uploaded_images/default_img.png"}, "sub_117": {"id": 117, "mode": "website", "name_original": "", "name": "Play", "sub_name": "Win 40000", "website_url": "https://490.go.qureka.com/intro", "is_system_browser": true, "thumbnail_url": "https://raw.githubusercontent.com/kp-bitcoding/ad-manager/main/Interstitial/4.jpg", "thumbnail_url_original": ""}, "sub_118": {"id": 118, "mode": "video", "name": "Orange TV", "sub_name": "", "stream_video_url": "http://otv3.ocfl.net:1936/OrangeTV/smil:OrangeTV.smil/playlist.m3u8", "thumbnail_url": "https://www.iptv-updated.com/wp-content/themes/shootingstar-child/uploaded_images/default_img.png"}, "sub_119": {"id": 119, "mode": "video", "name": "QVC 2", "sub_name": "", "stream_video_url": "https://lsqvc2us-lh.akamaihd.net/i/lsqvc2us_01@809440/master.m3u8", "thumbnail_url": "https://www.iptv-updated.com/wp-content/themes/shootingstar-child/uploaded_images/default_img.png"}, "sub_120": {"id": 120, "mode": "website", "name_original": "", "name": "Play", "sub_name": "Win 50000", "website_url": "https://490.go.qureka.com/intro", "is_system_browser": true, "thumbnail_url": "https://raw.githubusercontent.com/kp-bitcoding/ad-manager/main/Interstitial/5.jpg", "thumbnail_url_original": ""}, "sub_121": {"id": 121, "mode": "video", "name": "QVC 3", "sub_name": "", "stream_video_url": "https://lsqvc3us-lh.akamaihd.net/i/lsqvc3us_01@809459/master.m3u8", "thumbnail_url": "https://www.iptv-updated.com/wp-content/themes/shootingstar-child/uploaded_images/default_img.png"}, "sub_122": {"id": 122, "mode": "video", "name": "QVC 3", "sub_name": "", "stream_video_url": "https://v-pi.mybtv.net/event/41.4/640x480?start_time=2019-12-13T21%3A45%3A00.000Z&end_time=2026&env=prd&uid=29375", "thumbnail_url": "https://www.iptv-updated.com/wp-content/themes/shootingstar-child/uploaded_images/default_img.png"}, "sub_123": {"id": 123, "mode": "website", "name_original": "", "name": "Play", "sub_name": "Win 60000", "website_url": "https://490.go.qureka.com/intro", "is_system_browser": true, "thumbnail_url": "https://raw.githubusercontent.com/kp-bitcoding/ad-manager/main/Interstitial/6.jpg", "thumbnail_url_original": ""}, "sub_124": {"id": 124, "mode": "video", "name": "Revelation TV", "sub_name": "", "stream_video_url": "https://rtv.cdn.mangomolo.com/rtv/smil:switch.smil/playlist.m3u8", "thumbnail_url": "https://www.iptv-updated.com/wp-content/themes/shootingstar-child/uploaded_images/revelation_tv_img_2752.png"}, "sub_125": {"id": 125, "mode": "video", "name": "Shop HQ", "sub_name": "", "stream_video_url": "https://aos01-evine.secure.footprint.net/evine/cleanfeed/VIDEO_0_2064000.m3u8", "thumbnail_url": "https://www.iptv-updated.com/wp-content/themes/shootingstar-child/uploaded_images/shop_hq_img_2763.png"}, "sub_126": {"id": 126, "mode": "website", "name_original": "", "name": "Play", "sub_name": "Win 70000", "website_url": "https://490.go.qureka.com/intro", "is_system_browser": true, "thumbnail_url": "https://raw.githubusercontent.com/kp-bitcoding/ad-manager/main/Interstitial/7.jpg", "thumbnail_url_original": ""}, "sub_127": {"id": 127, "mode": "video", "name": "Shop HQ", "sub_name": "", "stream_video_url": "https://aos01-evine.secure.footprint.net/evine/cleanfeed/master.m3u8", "thumbnail_url": "https://www.iptv-updated.com/wp-content/themes/shootingstar-child/uploaded_images/shop_hq_img_2763.png"}, "sub_128": {"id": 128, "mode": "video", "name": "TBD", "sub_name": "", "stream_video_url": "http://content.uplynk.com/channel/1831163f97674328ad9f4b4814ed39c5.m3u8", "thumbnail_url": "https://www.iptv-updated.com/wp-content/themes/shootingstar-child/uploaded_images/tbd_img_2773.png"}, "sub_129": {"id": 129, "mode": "website", "name_original": "", "name": "Play", "sub_name": "Win 10000", "website_url": "https://490.go.qureka.com/intro", "is_system_browser": true, "thumbnail_url": "https://raw.githubusercontent.com/kp-bitcoding/ad-manager/main/Interstitial/1.jpg", "thumbnail_url_original": ""}, "sub_130": {"id": 130, "mode": "video", "name": "TBD", "sub_name": "", "stream_video_url": "https://content.uplynk.com/channel/1831163f97674328ad9f4b4814ed39c5.m3u8", "thumbnail_url": "https://www.iptv-updated.com/wp-content/themes/shootingstar-child/uploaded_images/tbd_img_2773.png"}, "sub_131": {"id": 131, "mode": "video", "name": "TBD", "sub_name": "", "stream_video_url": "https://content.uplynk.com/channel/1831163f97674328ad9f4b4814ed39c5.m3u8?tc=1&exp=1614631202&rn=614441536&ct=c&cid=1831163f97674328ad9f4b4814ed39c5&ad=comet&ad.adUnit=%2FTBD%2FLivestream_midroll&ad._debug=TBDNET_ssai_livestream_midroll&ad.ad_rule=1&ad.pmad=12&ad.output=xml_vmap1&sig=5d194a4e4c5a4d59023d6a39a2ba5ba82dcd817b615e9f82115c41d9b26ffd0a", "thumbnail_url": "https://www.iptv-updated.com/wp-content/themes/shootingstar-child/uploaded_images/tbd_img_2773.png"}, "sub_132": {"id": 132, "mode": "website", "name_original": "", "name": "Play", "sub_name": "Win 20000", "website_url": "https://490.go.qureka.com/intro", "is_system_browser": true, "thumbnail_url": "https://raw.githubusercontent.com/kp-bitcoding/ad-manager/main/Interstitial/2.jpg", "thumbnail_url_original": ""}, "sub_133": {"id": 133, "mode": "video", "name": "Tempe 11", "sub_name": "", "stream_video_url": "https://granicusliveus1-a.akamaihd.net/tempe/G0355_003/chunklist.m3u8", "thumbnail_url": "https://www.iptv-updated.com/wp-content/themes/shootingstar-child/uploaded_images/tempe_11_img_2777.png"}, "sub_134": {"id": 134, "mode": "video", "name": "The Now Network", "sub_name": "", "stream_video_url": "https://link.frontlayer.com/services/hls2/fl619843/index.m3u8", "thumbnail_url": "https://www.iptv-updated.com/wp-content/themes/shootingstar-child/uploaded_images/the_now_network_img_2784.png"}, "sub_135": {"id": 135, "mode": "website", "name_original": "", "name": "Play", "sub_name": "Win 30000", "website_url": "https://490.go.qureka.com/intro", "is_system_browser": true, "thumbnail_url": "https://raw.githubusercontent.com/kp-bitcoding/ad-manager/main/Interstitial/3.jpg", "thumbnail_url_original": ""}, "sub_136": {"id": 136, "mode": "video", "name": "WCCA-TV (Worcester)", "sub_name": "", "stream_video_url": "http://worcester.vod.castus.tv/live/ch1.m3u8?fluxustv.m3u8", "thumbnail_url": "https://www.iptv-updated.com/wp-content/themes/shootingstar-child/uploaded_images/wcca-tv_(worcester)_img_2809.png"}, "sub_137": {"id": 137, "mode": "video", "name": "WCCA-TV (Worcester)", "sub_name": "", "stream_video_url": "https://worcester.vod.castus.tv/live/ch1.m3u8", "thumbnail_url": "https://www.iptv-updated.com/wp-content/themes/shootingstar-child/uploaded_images/wcca-tv_(worcester)_img_2809.png"}, "sub_138": {"id": 138, "mode": "website", "name_original": "", "name": "Play", "sub_name": "Win 40000", "website_url": "https://490.go.qureka.com/intro", "is_system_browser": true, "thumbnail_url": "https://raw.githubusercontent.com/kp-bitcoding/ad-manager/main/Interstitial/4.jpg", "thumbnail_url_original": ""}, "sub_139": {"id": 139, "mode": "video", "name": "3ABN Latino", "sub_name": "", "stream_video_url": "https://moiptvhls-i.akamaihd.net/hls/live/652315/secure/master.m3u8", "thumbnail_url": "https://www.iptv-updated.com/wp-content/themes/shootingstar-child/uploaded_images/3abn_latino_img_2474.png"}, "sub_140": {"id": 140, "mode": "video", "name": "WPEC CBS12 News", "sub_name": "", "stream_video_url": "https://content.uplynk.com/channel/0123b306191a4307a31b9fb573213fd3.m3u8", "thumbnail_url": ""}}}}}}